Metadata-Version: 2.1
Name: HaiChatbot
Version: 0.0.4
Summary: chatbot
Home-page: https://github.com/Happleasei/HaiHai
Author: Wang Hai
Author-email: nicewanghai@163.com
Classifier: Programming Language :: Python :: 3
Classifier: License :: OSI Approved :: MIT License
Classifier: Operating System :: OS Independent
